onnx_clip/__init__.py
onnx_clip/cli.py
onnx_clip/exporter.py
onnx_clip/model.py
onnx_clip/preprocessor.py
onnx_clip/tokenizer.py
modern_onnx_clip-0.1.3.dist-info/METADATA
modern_onnx_clip-0.1.3.dist-info/WHEEL
modern_onnx_clip-0.1.3.dist-info/entry_points.txt
modern_onnx_clip-0.1.3.dist-info/licenses/LICENSE
modern_onnx_clip-0.1.3.dist-info/RECORD
