Metadata-Version: 2.4
Name: modern-onnx-clip
Version: 0.1.3
Summary: A production-ready, zero-dependency ONNX runtime for OpenAI CLIP and OpenCLIP models.
Project-URL: Homepage, https://github.com/Neizvestnyj/modern-onnx-clip
Project-URL: Repository, https://github.com/Neizvestnyj/modern-onnx-clip
Project-URL: Issues, https://github.com/Neizvestnyj/modern-onnx-clip/issues
Project-URL: Documentation, https://github.com/Neizvestnyj/modern-onnx-clip#readme
Author: Modern ONNX CLIP Contributors
License: MIT
License-File: LICENSE
Classifier: Development Status :: 4 - Beta
Classifier: Intended Audience :: Developers
Classifier: License :: OSI Approved :: MIT License
Classifier: Programming Language :: Python :: 3
Classifier: Programming Language :: Python :: 3.10
Classifier: Programming Language :: Python :: 3.11
Classifier: Programming Language :: Python :: 3.12
Classifier: Topic :: Scientific/Engineering :: Artificial Intelligence
Requires-Python: >=3.10
Requires-Dist: ftfy>=6.1.0
Requires-Dist: numpy>=2.0.0
Requires-Dist: onnxruntime>=1.17.0
Requires-Dist: pillow>=10.2.0
Requires-Dist: regex>=2023.10.0
Requires-Dist: requests>=2.31.0
Requires-Dist: tokenizers>=0.19.0
Provides-Extra: dev
Requires-Dist: pre-commit>=3.6.0; extra == 'dev'
Requires-Dist: pyright>=1.1.350; extra == 'dev'
Requires-Dist: pytest-cov>=4.1.0; extra == 'dev'
Requires-Dist: pytest>=8.0.0; extra == 'dev'
Requires-Dist: ruff>=0.3.0; extra == 'dev'
Provides-Extra: export
Requires-Dist: onnx>=1.15.0; extra == 'export'
Requires-Dist: onnxscript>=0.1.0; extra == 'export'
Requires-Dist: open-clip-torch>=2.24.0; extra == 'export'
Requires-Dist: torch>=2.2.0; extra == 'export'
